<?xml version="1.0" encoding="utf-8" ?><dwsync><file name="15east.PNG" server="ftp.techteach.us" local="3516545368" remote="3517211340" Dst="-1" /><file name="b.PNG" server="ftp.techteach.us" local="3516545438" remote="3517211340" Dst="-1" /><file name="blackseed.PNG" server="ftp.techteach.us" local="3516544430" remote="3517211340" Dst="-1" /><file name="buv.PNG" server="ftp.techteach.us" local="3516546096" remote="3517211340" Dst="-1" /><file name="delp.PNG" server="ftp.techteach.us" local="3516546160" remote="3517211340" Dst="-1" /><file name="fettesau.PNG" server="ftp.techteach.us" local="3516544322" remote="3517211340" Dst="-1" /><file name="kaji.PNG" server="ftp.techteach.us" local="3516546226" remote="3517211340" Dst="-1" /><file name="narcissa.PNG" server="ftp.techteach.us" local="3516543640" remote="3517211340" Dst="-1" /><file name="mp.PNG" server="ftp.techteach.us" local="3516546001" remote="3517211340" Dst="-1" /><file name="nb.PNG" server="ftp.techteach.us" local="3516545623" remote="3517211340" Dst="-1" /><file name="rf.PNG" server="ftp.techteach.us" local="3516545298" remote="3517211340" Dst="-1" /><file name="roberta.PNG" server="ftp.techteach.us" local="3516544155" remote="3517211340" Dst="-1" /><file name="spottedpig.PNG" server="ftp.techteach.us" local="3516544601" remote="3517211340" Dst="-1" /><file name="tert.PNG" server="ftp.techteach.us" local="3516546278" remote="3517211340" Dst="-1" /><file name="tt.PNG" server="ftp.techteach.us" local="3516545182" remote="3517211340" Dst="-1" /></dwsync>